README.md
setup.py
django_query_parser.egg-info/PKG-INFO
django_query_parser.egg-info/SOURCES.txt
django_query_parser.egg-info/dependency_links.txt
django_query_parser.egg-info/top_level.txt
django_query_parser.egg-info/zip-safe
query_parser/Parser.py
query_parser/__init__.py
query_parser/apps.py
query_parser/tests.py