Metadata-Version: 2.1
Name: django-query-parser
Version: 0.0.3
Summary: A django app to store and load partial queries from external  sources
Home-page: https://github.com/mkalioby/django-query-parser/
Author: Mohamed El-Kalioby
Author-email: mkalioby@mkalioby.com
License: MIT
Download-URL: https://github.com/mkalioby/django-query-parser/
Platform: UNKNOWN
Classifier: Development Status :: 5 - Production/Stable
Classifier: Environment :: Web Environment
Classifier: Framework :: Django
Classifier: Framework :: Django :: 1.11
Classifier: Framework :: Django :: 2.0
Classifier: Framework :: Django :: 2.1
Classifier: Framework :: Django :: 2.2
Classifier: Intended Audience :: Developers
Classifier: Operating System :: OS Independent
Classifier: Programming Language :: Python
Classifier: Programming Language :: Python :: 3
Classifier: Programming Language :: Python :: 3.5
Classifier: Programming Language :: Python :: 3.6
Classifier: Programming Language :: Python :: 3.7
Classifier: Programming Language :: Python :: 3.8
Classifier: Topic :: Software Development :: Libraries :: Python Modules
Requires-Python: >=3.5
